LICENSE.txt
MANIFEST.in
README.rst
setup.cfg
setup.py
pyhomematic/__init__.py
pyhomematic/_hm.py
pyhomematic/connection.py
pyhomematic/exceptions.py
pyhomematic/vccu.py
pyhomematic.egg-info/PKG-INFO
pyhomematic.egg-info/SOURCES.txt
pyhomematic.egg-info/dependency_links.txt
pyhomematic.egg-info/not-zip-safe
pyhomematic.egg-info/top_level.txt
pyhomematic/devicetypes/__init__.py
pyhomematic/devicetypes/actors.py
pyhomematic/devicetypes/generic.py
pyhomematic/devicetypes/helper.py
pyhomematic/devicetypes/misc.py
pyhomematic/devicetypes/sensors.py
pyhomematic/devicetypes/thermostats.py
pyhomematic/devicetypes/json/device_descriptions.json
pyhomematic/devicetypes/json/device_details.json
tests/__init__.py
tests/test_pyhomematic.py