Metadata-Version: 1.1
Name: pyhomematic
Version: 0.1.70
Summary: Homematic interface
Home-page: https://github.com/danielperna84/pyhomematic
Author: Daniel Perna
Author-email: danielperna84@gmail.com
License: MIT License
Download-URL: https://github.com/danielperna84/pyhomematic/tarball/0.1.70
Keywords: home,automation,homematic,smarthome
Platform: any
Classifier: Intended Audience :: Developers
Classifier: License :: OSI Approved :: MIT License
Classifier: Operating System :: OS Independent
Classifier: Programming Language :: Python :: 3.5
Classifier: Topic :: Home Automation
